Metadata-Version: 2.1
Name: boosted-trees
Version: 0.0.0
Summary: Boosted Trees
Home-page: https://github.com/blester125/boosted_trees
Author: blester125
Author-email: blester125@gmail.com
License: MIT
Download-URL: https://github.com/blester125/boosted_trees/archive/0.0.0.tar.gz
Platform: UNKNOWN
Classifier: Development Status :: 3 - Alpha
Classifier: License :: OSI Approved :: MIT License
Classifier: Intended Audience :: Science/Research
Classifier: Programming Language :: Python :: 3 :: Only
Classifier: Natural Language :: English
Classifier: Topic :: Scientific/Engineering
Classifier: Intended Audience :: Developers
Classifier: Environment :: Console
Requires-Python: >=3.6
Provides-Extra: test
